{
    "boxShadow": "{{appsmith.theme.boxShadow.appBoxShadow}}",
    "borderColor": "#E0DEDE",
    "isVisibleDownload": false,
    "iconSVG": "/static/media/icon.e6911f8bb94dc6c4a102a74740c41763.svg",
    "topRow": 14,
    "isSortable": true,
    "type": "TABLE_WIDGET_V2",
    "inlineEditingSaveOption": "ROW_LEVEL",
    "animateLoading": true,
    "dynamicBindingPathList": [
        {"key": "accentColor"},
        {"key": "borderRadius"},
        {"key": "boxShadow"},
        {"key": "tableData"},
        {"key": "primaryColumns.address.computedValue"},
        {"key": "primaryColumns.cafe_name.computedValue"},
        {"key": "primaryColumns.days.computedValue"},
        {"key": "primaryColumns.time.computedValue"},
        {"key": "primaryColumns.customColumn1.borderRadius"},
        {"key": "primaryColumns.customColumn1.boxShadow"},
        {"key": "primaryColumns.customColumn2.borderRadius"},
        {"key": "primaryColumns.customColumn2.boxShadow"},
        {"key": "primaryColumns.cafe_id.computedValue"}
    ],
    "needsHeightForContent": true,
    "leftColumn": 2,
    "delimiter": ",",
    "defaultSelectedRowIndex": 0,
    "flexVerticalAlignment": "start",
    "accentColor": "{{appsmith.theme.colors.primaryColor}}",
    "isVisibleFilters": true,
    "isVisible": true,
    "enableClientSideSearch": true,
    "version": 2,
    "totalRecordsCount": 0,
    "tags": [
        "Suggested",
        "Display"
    ],
    "isLoading": false,
    "onSearchTextChanged": "{{}}",
    "childStylesheet": {
        "button": {
            "boxShadow": "none",
            "borderRadius": "{{appsmith.theme.borderRadius.appBorderRadius}}",
            "buttonColor": "{{appsmith.theme.colors.primaryColor}}"
        },
        "iconButton": {
            "boxShadow": "none",
            "borderRadius": "{{appsmith.theme.borderRadius.appBorderRadius}}",
            "buttonColor": "{{appsmith.theme.colors.primaryColor}}"
        },
        "menuButton": {
            "boxShadow": "none",
            "borderRadius": "{{appsmith.theme.borderRadius.appBorderRadius}}",
            "menuColor": "{{appsmith.theme.colors.primaryColor}}"
        },
        "editActions": {
            "saveButtonColor": "{{appsmith.theme.colors.primaryColor}}",
            "saveBorderRadius": "{{appsmith.theme.borderRadius.appBorderRadius}}",
            "discardBorderRadius": "{{appsmith.theme.borderRadius.appBorderRadius}}",
            "discardButtonColor": "{{appsmith.theme.colors.primaryColor}}"
        }
    },
    "borderRadius": "{{appsmith.theme.borderRadius.appBorderRadius}}",
    "columnUpdatedAt": 1701877835549,
    "defaultSelectedRowIndices": [0],
    "mobileBottomRow": 55,
    "widgetName": "Table1",
    "defaultPageSize": 0,
    "columnOrder": [
        "address",
        "cafe_name",
        "days",
        "time",
        "customColumn1",
        "customColumn2",
        "cafe_id"
    ],
    "dynamicPropertyPathList": [{"key": "onSearchTextChanged"}],
    "displayName": "Table",
    "bottomRow": 305,
    "columnWidthMap": {},
    "parentRowSpace": 10,
    "hideCard": false,
    "mobileRightColumn": 25,
    "parentColumnSpace": 19.8125,
    "dynamicTriggerPathList": [
        {"key": "primaryColumns.customColumn1.onClick"},
        {"key": "primaryColumns.customColumn2.onClick"}
    ],
    "borderWidth": "1",
    "primaryColumns": {
        "cafe_name": {
            "computedValue": "{{Table1.processedTableData.map((currentRow, currentIndex) => ( currentRow[\"cafe_name\"]))}}",
            "isEditable": false,
            "notation": "standard",
            "alias": "cafe_name",
            "enableSort": true,
            "isSaveVisible": true,
            "id": "cafe_name",
            "isDisabled": false,
            "allowSameOptionsInNewRow": true,
            "validation": {},
            "isCellVisible": true,
            "isDerived": false,
            "textSize": "0.875rem",
            "allowCellWrapping": false,
            "index": 1,
            "isDiscardVisible": true,
            "isVisible": true,
            "label": "cafe_name",
            "fontStyle": "",
            "textColor": "",
            "columnType": "text",
            "thousandSeparator": true,
            "horizontalAlignment": "LEFT",
            "isCellEditable": false,
            "decimals": 0,
            "width": 150,
            "enableFilter": true,
            "sticky": "",
            "originalId": "cafe_name",
            "currencyCode": "USD",
            "cellBackground": "",
            "verticalAlignment": "CENTER"
        },
        "address": {
            "computedValue": "{{Table1.processedTableData.map((currentRow, currentIndex) => ( currentRow[\"address\"]))}}",
            "isEditable": false,
            "notation": "standard",
            "alias": "address",
            "enableSort": true,
            "isSaveVisible": true,
            "id": "address",
            "isDisabled": false,
            "allowSameOptionsInNewRow": true,
            "validation": {},
            "isCellVisible": true,
            "isDerived": false,
            "textSize": "0.875rem",
            "allowCellWrapping": false,
            "index": 0,
            "isDiscardVisible": true,
            "isVisible": true,
            "label": "address",
            "fontStyle": "",
            "textColor": "",
            "columnType": "text",
            "thousandSeparator": true,
            "horizontalAlignment": "LEFT",
            "isCellEditable": false,
            "decimals": 0,
            "width": 150,
            "enableFilter": true,
            "sticky": "",
            "originalId": "address",
            "currencyCode": "USD",
            "cellBackground": "",
            "verticalAlignment": "CENTER"
        },
        "cafe_id": {
            "computedValue": "{{Table1.processedTableData.map((currentRow, currentIndex) => ( currentRow[\"cafe_id\"]))}}",
            "isEditable": false,
            "notation": "standard",
            "alias": "cafe_id",
            "enableSort": true,
            "isSaveVisible": true,
            "id": "cafe_id",
            "isDisabled": false,
            "allowSameOptionsInNewRow": true,
            "validation": {},
            "isCellVisible": true,
            "isDerived": false,
            "textSize": "0.875rem",
            "allowCellWrapping": false,
            "index": 1,
            "isDiscardVisible": true,
            "isVisible": false,
            "label": "cafe_id",
            "fontStyle": "",
            "textColor": "",
            "columnType": "number",
            "thousandSeparator": true,
            "horizontalAlignment": "LEFT",
            "isCellEditable": false,
            "decimals": 0,
            "width": 150,
            "enableFilter": true,
            "sticky": "",
            "originalId": "cafe_id",
            "currencyCode": "USD",
            "cellBackground": "",
            "verticalAlignment": "CENTER"
        },
        "days": {
            "computedValue": "{{Table1.processedTableData.map((currentRow, currentIndex) => ( currentRow[\"days\"]))}}",
            "isEditable": false,
            "notation": "standard",
            "alias": "days",
            "enableSort": true,
            "isSaveVisible": true,
            "id": "days",
            "isDisabled": false,
            "allowSameOptionsInNewRow": true,
            "validation": {},
            "isCellVisible": true,
            "isDerived": false,
            "textSize": "0.875rem",
            "allowCellWrapping": false,
            "index": 2,
            "isDiscardVisible": true,
            "isVisible": true,
            "label": "days",
            "fontStyle": "",
            "textColor": "",
            "columnType": "text",
            "thousandSeparator": true,
            "horizontalAlignment": "LEFT",
            "isCellEditable": false,
            "decimals": 0,
            "width": 150,
            "enableFilter": true,
            "sticky": "",
            "originalId": "days",
            "currencyCode": "USD",
            "cellBackground": "",
            "verticalAlignment": "CENTER"
        },
        "customColumn1": {
            "boxShadow": "{{Table1.processedTableData.map((currentRow, currentIndex) => ( \"none\"))}}",
            "computedValue": "",
            "onClick": "{{navigateTo('Screen 7A', currentRow.cafe_id, 'SAME_WINDOW');\nstoreValue('cafe_id', currentRow.cafe_id);}}",
            "buttonColor": "#f2dbb6",
            "isEditable": false,
            "notation": "standard",
            "alias": "",
            "enableSort": true,
            "isSaveVisible": true,
            "id": "customColumn1",
            "isDisabled": false,
            "allowSameOptionsInNewRow": true,
            "validation": {},
            "isCellVisible": true,
            "isDerived": true,
            "textSize": "0.875rem",
            "buttonStyle": "rgb(3, 179, 101)",
            "allowCellWrapping": false,
            "index": 4,
            "isDiscardVisible": true,
            "isVisible": true,
            "label": "",
            "labelColor": "#FFFFFF",
            "buttonLabel": "View Cafe",
            "columnType": "button",
            "thousandSeparator": true,
            "horizontalAlignment": "LEFT",
            "isCellEditable": false,
            "borderRadius": "{{Table1.processedTableData.map((currentRow, currentIndex) => ( (appsmith.theme.borderRadius.appBorderRadius)))}}",
            "decimals": 0,
            "width": 150,
            "enableFilter": true,
            "sticky": "",
            "originalId": "customColumn1",
            "currencyCode": "USD",
            "customAlias": "",
            "verticalAlignment": "CENTER"
        },
        "time": {
            "computedValue": "{{Table1.processedTableData.map((currentRow, currentIndex) => ( currentRow[\"time\"]))}}",
            "isEditable": false,
            "notation": "standard",
            "alias": "time",
            "enableSort": true,
            "isSaveVisible": true,
            "id": "time",
            "isDisabled": false,
            "allowSameOptionsInNewRow": true,
            "validation": {},
            "isCellVisible": true,
            "isDerived": false,
            "textSize": "0.875rem",
            "allowCellWrapping": false,
            "index": 3,
            "isDiscardVisible": true,
            "isVisible": true,
            "label": "time",
            "fontStyle": "",
            "textColor": "",
            "columnType": "text",
            "thousandSeparator": true,
            "horizontalAlignment": "LEFT",
            "isCellEditable": false,
            "decimals": 0,
            "width": 150,
            "enableFilter": true,
            "sticky": "",
            "originalId": "time",
            "currencyCode": "USD",
            "cellBackground": "",
            "verticalAlignment": "CENTER"
        },
        "customColumn2": {
            "boxShadow": "{{Table1.processedTableData.map((currentRow, currentIndex) => ( \"none\"))}}",
            "computedValue": "",
            "onClick": "{{storeValue('delete_cafe_id', currentRow.cafe_id);\nApi4.run().then(() => {\n  Api3.run();\n});}}",
            "buttonColor": "#f2dbb6",
            "isEditable": false,
            "notation": "standard",
            "alias": "",
            "enableSort": true,
            "isSaveVisible": true,
            "id": "customColumn2",
            "isDisabled": false,
            "allowSameOptionsInNewRow": true,
            "validation": {},
            "isCellVisible": true,
            "isDerived": true,
            "textSize": "0.875rem",
            "buttonStyle": "rgb(3, 179, 101)",
            "allowCellWrapping": false,
            "index": 5,
            "isDiscardVisible": true,
            "isVisible": true,
            "label": "",
            "labelColor": "#FFFFFF",
            "buttonLabel": "Delete Cafe",
            "columnType": "button",
            "thousandSeparator": true,
            "horizontalAlignment": "LEFT",
            "isCellEditable": false,
            "borderRadius": "{{Table1.processedTableData.map((currentRow, currentIndex) => ( (appsmith.theme.borderRadius.appBorderRadius)))}}",
            "decimals": 0,
            "width": 150,
            "enableFilter": true,
            "sticky": "",
            "originalId": "customColumn2",
            "currencyCode": "USD",
            "customAlias": "",
            "verticalAlignment": "CENTER"
        }
    },
    "key": "vw3cr35ydk",
    "canFreezeColumn": true,
    "isDeprecated": false,
    "rightColumn": 62,
    "textSize": "0.875rem",
    "widgetId": "dr660blviq",
    "minWidth": 450,
    "tableData": "{{Api3.data}}",
    "label": "Data",
    "searchKey": "",
    "parentId": "0",
    "serverSidePaginationEnabled": false,
    "renderMode": "CANVAS",
    "mobileTopRow": 27,
    "horizontalAlignment": "LEFT",
    "isVisibleSearch": true,
    "responsiveBehavior": "fill",
    "mobileLeftColumn": 0,
    "isVisiblePagination": true,
    "verticalAlignment": "CENTER"
}